ahelper/__init__.py
ahelper/deepwalk.py
ahelper/feature.py
ahelper/layers.py
ahelper/links.py
ahelper/nlu_lora.py
ahelper/snn.py
ahelper/utils.py
ahelper/medicalgpt/chatpdf.py
ahelper/medicalgpt/convert_dataset.py
ahelper/medicalgpt/deepspeed_zero_stage2_config.json
ahelper/medicalgpt/deepspeed_zero_stage3_config.json
ahelper/medicalgpt/dpo_training.py
ahelper/medicalgpt/fastapi_server_demo.py
ahelper/medicalgpt/gradio_demo.py
ahelper/medicalgpt/inference.py
ahelper/medicalgpt/inference_multigpu_demo.py
ahelper/medicalgpt/merge_peft_adapter.py
ahelper/medicalgpt/merge_tokenizers.py
ahelper/medicalgpt/openai_api.py
ahelper/medicalgpt/orpo_training.py
ahelper/medicalgpt/ppo_training.py
ahelper/medicalgpt/pretraining.py
ahelper/medicalgpt/reward_modeling.py
ahelper/medicalgpt/run_dpo.sh
ahelper/medicalgpt/run_orpo.sh
ahelper/medicalgpt/run_ppo.sh
ahelper/medicalgpt/run_pt.sh
ahelper/medicalgpt/run_rm.sh
ahelper/medicalgpt/run_sft.sh
ahelper/medicalgpt/run_training_dpo_pipeline.ipynb
ahelper/medicalgpt/run_training_ppo_pipeline.ipynb
ahelper/medicalgpt/supervised_finetuning.py
ahelper-1.3.2.dist-info/METADATA
ahelper-1.3.2.dist-info/WHEEL
ahelper-1.3.2.dist-info/top_level.txt
ahelper-1.3.2.dist-info/RECORD
